{
  "generatedAt": "2026-05-20T02:18:45.986Z",
  "overallStatus": "FAIL",
  "activeTarget": "https://parselradar-production.up.railway.app",
  "commitHash": "e5b9b54f2ca42c7187e9383c815b868748fcd0b6",
  "proofs": {
    "railwayActiveDeploymentProof": {
      "status": "FAIL",
      "detail": "No candidate responded with JSON health."
    },
    "activeApiUrlProof": {
      "status": "PASS",
      "detail": "Active API URL resolved to https://parselradar-production.up.railway.app"
    },
    "healthProof": {
      "status": "FAIL",
      "detail": "Unexpected response status=502, contentType=application/json",
      "url": "https://parselradar-production.up.railway.app/health",
      "statusCode": 502,
      "contentType": "application/json",
      "allowOrigin": null,
      "allowCredentials": null,
      "allowHeaders": null,
      "allowMethods": null,
      "bodyPreview": "{\"status\":\"error\",\"code\":502,\"message\":\"Application failed to respond\",\"request_id\":\"vSgbskyQRD2ajXbMvEOTxA\"}"
    },
    "buildInfoProof": {
      "status": "FAIL",
      "detail": "Unexpected response status=502, contentType=application/json",
      "url": "https://parselradar-production.up.railway.app/__buildinfo",
      "statusCode": 502,
      "contentType": "application/json",
      "allowOrigin": null,
      "allowCredentials": null,
      "allowHeaders": null,
      "allowMethods": null,
      "bodyPreview": "{\"status\":\"error\",\"code\":502,\"message\":\"Application failed to respond\",\"request_id\":\"6t6e1iNJQzSoEuFE2JZdWA\"}"
    },
    "authLoginOptionsProof": {
      "status": "FAIL",
      "detail": "Unexpected response status=502, contentType=application/json"
    },
    "forgotPasswordOptionsProof": {
      "status": "FAIL",
      "detail": "Unexpected response status=502, contentType=application/json"
    },
    "resetPasswordOptionsProof": {
      "status": "FAIL",
      "detail": "Unexpected response status=502, contentType=application/json"
    },
    "accessControlAllowOriginProof": {
      "status": "FAIL",
      "detail": "Observed ACAO values: login=none, forgot=none, reset=none"
    },
    "credentialsHeaderProof": {
      "status": "FAIL",
      "detail": "Observed ACC values: login=none, forgot=none, reset=none"
    },
    "allowedHeadersProof": {
      "status": "FAIL",
      "detail": "Observed ACAH values: login=none, forgot=none, reset=none"
    },
    "allowedMethodsProof": {
      "status": "FAIL",
      "detail": "Observed ACAM values: login=none, forgot=none, reset=none"
    },
    "forgotPasswordLiveProof": {
      "status": "FAIL",
      "detail": "Unexpected response status=502, contentType=application/json"
    },
    "noHtmlResponseProof": {
      "status": "PASS",
      "detail": "Checked that API endpoints did not return HTML bodies."
    },
    "buildInfoVisibleProof": {
      "status": "FAIL",
      "detail": "Unexpected response status=502, contentType=application/json"
    },
    "vercelViteApiUrlProof": {
      "status": "PASS",
      "detail": "Frontend API client points to the active Railway URL without a trailing slash."
    }
  }
}
